{
  "image_name": "captcha_00101.png",
  "text": "z6fGuU",
  "noise_coordinates": [
    [
      188,
      255
    ],
    [
      216,
      212
    ],
    [
      197,
      102
    ],
    [
      103,
      9
    ],
    [
      34,
      154
    ],
    [
      117,
      30
    ],
    [
      237,
      26
    ],
    [
      6,
      210
    ],
    [
      101,
      104
    ],
    [
      124,
      119
    ],
    [
      2,
      32
    ],
    [
      31,
      106
    ],
    [
      45,
      3
    ],
    [
      136,
      157
    ],
    [
      105,
      84
    ],
    [
      204,
      87
    ],
    [
      255,
      188
    ],
    [
      51,
      156
    ],
    [
      204,
      128
    ],
    [
      1,
      228
    ],
    [
      163,
      174
    ],
    [
      45,
      209
    ],
    [
      119,
      233
    ],
    [
      178,
      101
    ],
    [
      221,
      62
    ],
    [
      140,
      8
    ],
    [
      108,
      10
    ],
    [
      158,
      84
    ],
    [
      107,
      119
    ],
    [
      35,
      124
    ],
    [
      76,
      111
    ],
    [
      90,
      44
    ],
    [
      243,
      38
    ],
    [
      199,
      54
    ],
    [
      216,
      86
    ],
    [
      93,
      130
    ],
    [
      78,
      118
    ],
    [
      154,
      167
    ],
    [
      51,
      212
    ],
    [
      99,
      128
    ],
    [
      203,
      62
    ],
    [
      121,
      122
    ],
    [
      69,
      143
    ],
    [
      206,
      83
    ],
    [
      155,
      111
    ],
    [
      247,
      147
    ],
    [
      234,
      162
    ],
    [
      3,
      74
    ],
    [
      24,
      70
    ],
    [
      167,
      18
    ],
    [
      51,
      52
    ],
    [
      182,
      13
    ],
    [
      207,
      6
    ],
    [
      175,
      80
    ],
    [
      112,
      36
    ],
    [
      137,
      243
    ],
    [
      131,
      207
    ],
    [
      131,
      252
    ],
    [
      71,
      122
    ],
    [
      217,
      132
    ],
    [
      246,
      192
    ],
    [
      104,
      107
    ],
    [
      75,
      61
    ],
    [
      138,
      103
    ],
    [
      34,
      186
    ],
    [
      190,
      63
    ],
    [
      9,
      108
    ],
    [
      78,
      4
    ],
    [
      238,
      32
    ],
    [
      192,
      161
    ],
    [
      47,
      146
    ],
    [
      199,
      67
    ],
    [
      9,
      176
    ],
    [
      124,
      168
    ],
    [
      162,
      199
    ],
    [
      11,
      106
    ],
    [
      125,
      116
    ],
    [
      198,
      134
    ],
    [
      217,
      103
    ],
    [
      123,
      28
    ],
    [
      97,
      227
    ],
    [
      173,
      198
    ],
    [
      133,
      203
    ],
    [
      130,
      200
    ],
    [
      87,
      134
    ],
    [
      216,
      14
    ],
    [
      233,
      23
    ],
    [
      23,
      16
    ],
    [
      63,
      146
    ],
    [
      84,
      10
    ],
    [
      29,
      136
    ],
    [
      99,
      186
    ],
    [
      30,
      108
    ],
    [
      103,
      238
    ],
    [
      149,
      111
    ],
    [
      201,
      71
    ],
    [
      146,
      167
    ],
    [
      101,
      172
    ],
    [
      79,
      99
    ],
    [
      244,
      181
    ],
    [
      207,
      41
    ],
    [
      60,
      164
    ],
    [
      14,
      15
    ],
    [
      168,
      169
    ],
    [
      177,
      255
    ],
    [
      23,
      158
    ]
  ],
  "line_coordinates": [
    [
      [
        81,
        71
      ],
      [
        165,
        93
      ]
    ],
    [
      [
        153,
        12
      ],
      [
        88,
        176
      ]
    ],
    [
      [
        199,
        187
      ],
      [
        225,
        192
      ]
    ],
    [
      [
        114,
        204
      ],
      [
        182,
        182
      ]
    ],
    [
      [
        182,
        208
      ],
      [
        90,
        189
      ]
    ]
  ],
  "noise_types": [
    "dot",
    "dot",
    "dot",
    "dot",
    "dot",
    "dot",
    "dot",
    "dot",
    "dot",
    "dot",
    "dot",
    "dot",
    "dot",
    "dot",
    "dot",
    "dot",
    "dot",
    "dot",
    "dot",
    "dot",
    "dot",
    "dot",
    "dot",
    "dot",
    "dot",
    "dot",
    "dot",
    "dot",
    "dot",
    "dot",
    "dot",
    "dot",
    "dot",
    "dot",
    "dot",
    "dot",
    "dot",
    "dot",
    "dot",
    "dot",
    "dot",
    "dot",
    "dot",
    "dot",
    "dot",
    "dot",
    "dot",
    "dot",
    "dot",
    "dot",
    "dot",
    "dot",
    "dot",
    "dot",
    "dot",
    "dot",
    "dot",
    "dot",
    "dot",
    "dot",
    "dot",
    "dot",
    "dot",
    "dot",
    "dot",
    "dot",
    "dot",
    "dot",
    "dot",
    "dot",
    "dot",
    "dot",
    "dot",
    "dot",
    "dot",
    "dot",
    "dot",
    "dot",
    "dot",
    "dot",
    "dot",
    "dot",
    "dot",
    "dot",
    "dot",
    "dot",
    "dot",
    "dot",
    "dot",
    "dot",
    "dot",
    "dot",
    "dot",
    "dot",
    "dot",
    "dot",
    "dot",
    "dot",
    "dot",
    "dot",
    "dot",
    "dot",
    "dot",
    "dot",
    "dot",
    "dot",
    "grid",
    "grid",
    "grid"
  ],
  "line_ids": [
    "uy9a4S8b",
    "ZD9UlzM3",
    "ztAXNNjW",
    "GxSq9n1t",
    "E1XjWPAU"
  ],
  "noise_ids": [
    "FPfKNrz2",
    "8Tzrt8uX",
    "Bn4hjky0",
    "UDcDLnnS",
    "IvJWGbcA",
    "d5l0EXJ4",
    "N8T6TqMN",
    "NQyIzarE",
    "kGzjP32x",
    "I802vuOo",
    "veJESxBF",
    "SHSpovtW",
    "9lVTVmGp",
    "DTW1umj5",
    "JUPJSieb",
    "iUMHhCVe",
    "hqMGyny0",
    "Pz2aIVNH",
    "XHkRg97j",
    "qCncE88s",
    "PmWIVNjZ",
    "w4MqEWcR",
    "ASc4bSOW",
    "oG0tZRbN",
    "HVAclgYb",
    "C90av64H",
    "qkLrYR8g",
    "n7BwpbkV",
    "bZgEb4sr",
    "Ntvu57Dc",
    "KxlB3bkx",
    "cGfqIRfc",
    "8FuGtkQY",
    "uQFMhPNp",
    "G0r8OYYN",
    "HBf0QyDZ",
    "KYu5KTVW",
    "a327sWQF",
    "PlDDD8cj",
    "zli1rJrx",
    "iwYesnTr",
    "eUKDPKIL",
    "9gHewalp",
    "ouTXvNaC",
    "zw2ngZSZ",
    "3I7JzZGF",
    "ayIdDyee",
    "9JE2DxJa",
    "eX8fRfzH",
    "71rFwjeY",
    "5EWJFBRU",
    "eIsy5hoy",
    "3HDrvosg",
    "5Gcoa5Yu",
    "vU7mOcjy",
    "GF4bqykB",
    "ezyp9UCI",
    "OfPDROX9",
    "uVrPceNw",
    "L8K7ytBK",
    "kxrzWKCz",
    "mPrC6hwN",
    "01aE6Q1b",
    "NC9XX5Mx",
    "NCpVBPNP",
    "Dqt5xP1s",
    "TauhdyQv",
    "KT79R6lX",
    "gudwhXjf",
    "H1OFvOnx",
    "zHCQjGg7",
    "JAiKEonK",
    "3UcGzbHl",
    "AchrdTF1",
    "2k7DTzoI",
    "qPtVaUza",
    "RH7SNmKN",
    "fQQe4RwF",
    "4G5X5TG8",
    "7Vxld2ps",
    "tHj6gCOx",
    "Mcd3N1gZ",
    "KQrtJZ5K",
    "leoIijgF",
    "7Si7fKZE",
    "avL2rbOB",
    "qAZs9aZw",
    "5zNoP5DA",
    "SKgt1ETf",
    "xBDqoztQ",
    "xkye0tM0",
    "lxe1eZiR",
    "inTstA5s",
    "m3ja7cqm",
    "3NGdqshy",
    "8WdfyKdC",
    "AFPpenY0",
    "tEq2hMzg",
    "5T9S7Dag",
    "on9qEZcU",
    "mU8GVC6r",
    "GI1biQun",
    "nlNUVM9b",
    "uaPZmzR0",
    "SJqOx22T",
    "Vrle4VjT",
    "2EIO6Hrq",
    "4TUCgMtS",
    "EOkpgrlw"
  ],
  "noise_level": 0.16313465651945416,
  "random_seed": 494802362,
  "bbox": [
    53,
    115,
    203,
    141
  ]
}